polypharm/__init__.py
polypharm/__main__.py
polypharm/concurrency.py
polypharm/helpers.py
polypharm/polypharm.py
polypharm/scripts/report.py
polypharm/templates/ifd.inp
polypharm-0.4.3.dist-info/LICENSE
polypharm-0.4.3.dist-info/METADATA
polypharm-0.4.3.dist-info/WHEEL
polypharm-0.4.3.dist-info/entry_points.txt
polypharm-0.4.3.dist-info/top_level.txt
polypharm-0.4.3.dist-info/RECORD
