Metadata-Version: 2.1
Name: polypharm
Version: 0.4.3
Summary: A Python-based library to perform IFD and MMGBSA calculations on different targets using a polypharmacological approach.
Author-email: Mauricio Bedoya <mbedoya@ucm.cl>, Francisco Adasme <fadasme@ucm.cl>
License: MIT License
Project-URL: Homepage, http://polypharm.rtfd.io/
Project-URL: Repository, https://github.com/ucm-lbqc/polypharm
Keywords: computational-chemistry,polypharmacology,molecular-docking,induced-fit,free-energy-calculations
Classifier: License :: OSI Approved :: MIT License
Classifier: Programming Language :: Python
Classifier: Programming Language :: Python :: 3
Classifier: Intended Audience :: Science/Research
Classifier: Topic :: Scientific/Engineering :: Bio-Informatics
Requires-Python: >=3.9
License-File: LICENSE
Requires-Dist: pandas >=1.4.3
Requires-Dist: jinja2 >=3.1.2
Provides-Extra: dev
Requires-Dist: black ; extra == 'dev'
Requires-Dist: isort ; extra == 'dev'
Requires-Dist: sphinx ; extra == 'dev'
Requires-Dist: sphinx-rtd-theme ; extra == 'dev'
